model_patch/__init__.py
model_patch/_version.py
transformers_ipfs/__init__.py
transformers_ipfs/_version.py
transformers_ipfs/cli.py
transformers_ipfs/patcher.py
transformers_ipfs-0.2.0.dist-info/METADATA
transformers_ipfs-0.2.0.dist-info/WHEEL
transformers_ipfs-0.2.0.dist-info/entry_points.txt
transformers_ipfs-0.2.0.dist-info/top_level.txt
transformers_ipfs-0.2.0.dist-info/RECORD
