Metadata-Version: 2.4
Name: transformers-ipfs
Version: 0.2.0
Summary: Enable IPFS model loading for Hugging Face Transformers
Author-email: Alex Baker <alex.baker.fon@protonmail.com>
License: MIT
Project-URL: Homepage, https://github.com/alexbakers/transformers_ipfs
Project-URL: Bug Tracker, https://github.com/alexbakers/transformers_ipfs/issues
Classifier: Programming Language :: Python :: 3
Classifier: Operating System :: OS Independent
Requires-Python: >=3.8
Requires-Dist: requests>=2.25.0
Provides-Extra: dev
Requires-Dist: black; extra == "dev"
Requires-Dist: isort; extra == "dev"
Requires-Dist: mypy; extra == "dev"
Requires-Dist: pytest; extra == "dev"
Requires-Dist: flake8; extra == "dev"
